{
  "Actor": {
    "types": ["player"],
    "player": {
      "bloodline": "",
      "origin": "",
      "post": "",
      "milestones": {
        "major": [],
        "minor": []
      },
      "drives": [],
      "mires": []
    }
  },
  "Item": {
    "types": ["aspect"],
    "templates": {
      "hasDetails": {
        "details": "",
        "collapsed": false
      },
      "hasTrack": {
        "track": {
          "value": 0
        }
      }
    },
    "aspect": {
      "templates": ["nasDetails", "hasTrack"],
      "track": { "max": 8 },
      "type": ""
    }
  }
}
